modak-0.3.10.dist-info/METADATA
modak-0.3.10.dist-info/WHEEL
modak-0.3.10.dist-info/entry_points.txt
modak-0.3.10.dist-info/licenses/LICENSE-APACHE
modak-0.3.10.dist-info/licenses/LICENSE-MIT
modak/__init__.py
modak/__init__.pyi
modak/__main__.py
modak/cli.py
modak/modak.cpython-313t-aarch64-linux-gnu.so
modak-0.3.10.dist-info/RECORD
