Metadata-Version: 2.4
Name: modak
Version: 0.3.10
Classifier: Development Status :: 3 - Alpha
Classifier: Programming Language :: Python :: 3.12
Classifier: Programming Language :: Python :: 3.13
Classifier: Programming Language :: Rust
Requires-Dist: click>=8.2.0
Requires-Dist: cloudpickle>=3.1.1
Requires-Dist: loguru>=0.7.3
Requires-Dist: numpy>=2.2.6
License-File: LICENSE-APACHE
License-File: LICENSE-MIT
Summary: A simple, opinionated task manager
Keywords: task,job,scheduler,monitor
Author-email: Nathaniel Dene Hoffman <dene@cmu.edu>
Requires-Python: >=3.12
Project-URL: Homepage, https://github.com/denehoffman/modak
Project-URL: Repository, https://github.com/denehoffman/modak
Project-URL: Issues, https://github.com/denehoffman/modak/issues
